dot/__init__.py
dot/__main__.py
dot/cli.py
dot/cli_prompts.py
dot/config.py
dot/dot.py
dot/git.py
dot/logging.py
dot/profiles.py
dot_for_dbt-0.5.0.dist-info/METADATA
dot_for_dbt-0.5.0.dist-info/WHEEL
dot_for_dbt-0.5.0.dist-info/entry_points.txt
dot_for_dbt-0.5.0.dist-info/licenses/LICENSE
dot_for_dbt-0.5.0.dist-info/RECORD
