Metadata-Version: 2.4
Name: dot-for-dbt
Version: 0.5.0
Summary: dot - the Data Orchestration Tool (for dbt)
Project-URL: Homepage, https://github.com/adammacleod/dot-for-dbt
Project-URL: Repository, https://github.com/adammacleod/dot-for-dbt
Project-URL: Issues, https://github.com/adammacleod/dot-for-dbt/issues
Author: Adam MacLeod
License: MIT License
License-File: LICENSE
Keywords: analytics,cli,data,dbt,orchestration,reproducibility
Classifier: Development Status :: 3 - Alpha
Classifier: Environment :: Console
Classifier: Intended Audience :: Developers
Classifier: License :: OSI Approved :: MIT License
Classifier: Operating System :: OS Independent
Classifier: Programming Language :: Python
Classifier: Programming Language :: Python :: 3
Classifier: Programming Language :: Python :: 3 :: Only
Classifier: Programming Language :: Python :: 3.12
Classifier: Programming Language :: Python :: 3.13
Classifier: Programming Language :: Python :: 3.14
Classifier: Programming Language :: Python :: 3.15
Classifier: Topic :: Database
Classifier: Topic :: Software Development :: Build Tools
Requires-Python: >=3.12
Requires-Dist: pyyaml>=6.0.2
Requires-Dist: rich>=13.0.0
Provides-Extra: dev
Requires-Dist: pytest>=8.0.0; extra == 'dev'
